{
  "essence": "1990_super_mario_world",
  "animation_name": "bowser_boss_room",
  "kind": "tile",
  "sub_kind": null,
  "frame_count": 2,
  "needs_animation": false,
  "base_prompt": "Pixel-art sprite of bowser_boss_room \u2014 a tile from 1990 super mario world. Bowser's Castle final-boss room \u2014 Clown Car arena. Centered on magenta (#FF00FF) background, 8-bit or 16-bit pixel-art aesthetic, no anti-aliasing, chunky pixels. Single canonical pose (frame 0 of animation).",
  "base_seed_label": "1990_super_mario_world_bowser_boss_room",
  "source_progression_description": "Bowser's Castle final-boss room \u2014 Clown Car arena",
  "nudges": []
}