{
  "essence": "1991_turtles_in_time",
  "animation_name": "metalhead",
  "kind": "character",
  "sub_kind": "boss",
  "frame_count": 16,
  "needs_animation": true,
  "base_prompt": "Pixel-art sprite of metalhead \u2014 a character (boss) from 1991 turtles in time. Metalhead \u2014 robot-turtle boss. Centered on magenta (#FF00FF) background, 8-bit or 16-bit pixel-art aesthetic, no anti-aliasing, chunky pixels. Single canonical pose (frame 0 of animation).",
  "base_seed_label": "1991_turtles_in_time_metalhead",
  "source_progression_description": "Metalhead \u2014 robot-turtle boss",
  "nudges": []
}